banking_system/__init__.py
banking_system/account.py
banking_system/customer.py
banking_system/transaction.py
banking_system-1.0.5.dist-info/METADATA
banking_system-1.0.5.dist-info/WHEEL
banking_system-1.0.5.dist-info/top_level.txt
banking_system-1.0.5.dist-info/RECORD
