Metadata-Version: 2.1
Name: banking-system
Version: 1.0.5
Summary: A simple banking management system package
Author: Kunal Kumar
